pexels_api_python/__init__.py
pexels_api_python/pexels_api.py
pexels_api_python-0.1.4.dist-info/METADATA
pexels_api_python-0.1.4.dist-info/WHEEL
pexels_api_python-0.1.4.dist-info/top_level.txt
pexels_api_python-0.1.4.dist-info/RECORD
